<?xml version="1.0" encoding="utf-8" ?>
<dwsync>
<file name="logo-mgs.svg" server="p21.es/www/" local="131811509888707450" remote="131770442400000000" Dst="0" />
<file name="sort_asc.png" server="p21.es/www/" local="131811509891467608" remote="131770442400000000" Dst="0" />
<file name="sort_asc_disabled.png" server="p21.es/www/" local="131811509899938093" remote="131770442400000000" Dst="0" />
<file name="sort_both.png" server="p21.es/www/" local="131811509913478867" remote="131770442400000000" Dst="0" />
<file name="sort_desc.png" server="p21.es/www/" local="131811509916449037" remote="131770442400000000" Dst="0" />
<file name="sort_desc_disabled.png" server="p21.es/www/" local="131811509963471375" remote="131770442400000000" Dst="0" />
<file name="sort_asc_disabled.png" server="f2m.quexulo.cat" local="131953156187884539" remote="131916137400000000" Dst="0" />
<file name="logo-mgs.svg" server="f2m.quexulo.cat" local="131953156190834708" remote="131916137400000000" Dst="0" />
<file name="sort_asc.png" server="f2m.quexulo.cat" local="131953156193934885" remote="131916137400000000" Dst="0" />
<file name="sort_both.png" server="f2m.quexulo.cat" local="131953156209125754" remote="131916137400000000" Dst="0" />
<file name="sort_desc_disabled.png" server="f2m.quexulo.cat" local="131953156218526292" remote="131916137400000000" Dst="0" />
<file name="sort_desc.png" server="f2m.quexulo.cat" local="131953156221416457" remote="131916137400000000" Dst="0" />
</dwsync>